{
  "players": [
    {
      "player": "Arrow",
      "score": 1,
      "joindate": 1476549472333,
      "lastactive": 1476550015090,
      "active": true
    },
    {
      "player": "EricIsADick",
      "score": 0,
      "joindate": 1476550105786,
      "lastactive": 1476550105786,
      "active": true
    },
    {
      "player": "EricIsADick",
      "score": 0,
      "joindate": 1476550117805,
      "lastactive": 1476550117806,
      "active": true
    },
    {
      "player": "Dj",
      "score": 0,
      "joindate": 1476550158247,
      "lastactive": 1476550172213,
      "active": true
    }
  ]
}
